subsplease/__init__.py
subsplease/api.py
subsplease/constants.py
subsplease/enums.py
subsplease/models.py
subsplease-1.0.4.dist-info/METADATA
subsplease-1.0.4.dist-info/WHEEL
subsplease-1.0.4.dist-info/top_level.txt
subsplease-1.0.4.dist-info/RECORD
