Metadata-Version: 2.1
Name: subsplease
Version: 1.0.4
Summary: A package for fetching and parsing episodes from SubsPlease API.
Home-page: https://github.com/praveensenpai/subsplease
Author: Praveen
Author-email: pvnt20@gmail.com
Requires-Python: >=3.11
Requires-Dist: httpx>=0.27.2
Requires-Dist: rich>=13.9.2
